Trees/AVLTree.py
Trees/BST.py
Trees/BinaryTree.py
Trees/Heap.py
Trees/__init__.py
Trees/__main__.py
Trees/feed.py
Trees/viewer.py
cs46_yismaeeltrees-1.1.0.dist-info/LICENSE
cs46_yismaeeltrees-1.1.0.dist-info/METADATA
cs46_yismaeeltrees-1.1.0.dist-info/WHEEL
cs46_yismaeeltrees-1.1.0.dist-info/top_level.txt
cs46_yismaeeltrees-1.1.0.dist-info/RECORD
